traval/__init__.py
traval/binary_classifier.py
traval/detector.py
traval/params.py
traval/plots.py
traval/rulelib.py
traval/ruleset.py
traval/ts_comparison.py
traval/ts_utils.py
traval/version.py
traval-0.5.2.dist-info/METADATA
traval-0.5.2.dist-info/WHEEL
traval-0.5.2.dist-info/top_level.txt
traval-0.5.2.dist-info/RECORD
